README
setup.py
PyMedium.egg-info/PKG-INFO
PyMedium.egg-info/SOURCES.txt
PyMedium.egg-info/dependency_links.txt
PyMedium.egg-info/requires.txt
PyMedium.egg-info/top_level.txt
pymedium/__init__.py
pymedium/api.py
pymedium/constant.py
pymedium/medium.py
pymedium/model.py
pymedium/parser.py