Metadata-Version: 1.0
Name: PyMedium
Version: 1.0.1
Summary: PyMedium - Unofficial Medium API
Home-page: https://github.com/enginebai/PyMedium
Author: Engine Bai
Author-email: enginebai@gmail.com
License: The MIT License (MIT) Copyright © 2017 Engine Bai.
Platform: UNKNOWN
